jasperClient/__init__.py
jasperClient/client.py
jasperClient-0.0.3.dist-info/METADATA
jasperClient-0.0.3.dist-info/WHEEL
jasperClient-0.0.3.dist-info/top_level.txt
jasperClient-0.0.3.dist-info/RECORD
